Workbook

Sheet pricing_chart
A2: EASY (for less than 15 garments) | I2: EASY (for less than 15 garments) | Q2: EASY (for less than 15 garments)
A6: WOMEN'S WEAR (Core , Ethnic , Western fusion / Nightwear) | I6: MEN'S WEAR (Core , Ethnic , Western fusion / Nightwear) | Q6: KID'S WEAR (Core , Ethnic , Western fusion / Nightwear)
A7: Category | B7: COS | C7: Tailor Cost | D7: Margin D2B | E7: D2B | F7: Margin D2C | G7: D2C | I7: Category | J7: COS | K7: Tailor Cost | L7: Margin D2B | M7: D2B | N7: Margin D2C | O7: D2C | Q7: Category | R7: COS | S7: Tailor Cost | T7: Margin D2B | U7: D2B | V7: Margin D2C | W7: D2C
A8: Short Kurti | B8: 184 | C8: 75 | D8: =E8-C8 -> 94 | E8: 169 | F8: =G8-C8 -> 174 | G8: 249 | I8: Shirt | J8: 233 | K8: 120 | L8: =M8-K8 -> 130 | M8: 250 | N8: =O8-K8 -> 180 | O8: 300 | Q8: School Uniform(girls) | R8: 399 - 699 | S8: 120 | T8: =U8-S8 -> 209 | U8: 329 | V8: =W8-U8 -> 170 | W8: 499
A9: Kurti | B9: 278 | C9: 90 | D9: =E9-C9 -> 129 | E9: 219 | F9: =G9-C9 -> 249 | G9: 339 | I9: T-Shirt | J9: 199 | K9: 80 | L9: =M9-K9 -> 100 | M9: 180 | N9: =O9-K9 -> 140 | O9: 220 | Q9: School Uniform(Boys) | R9: 350 - 599 | S9: 110 | T9: =U9-S9 -> 189 | U9: 299 | V9: =W9-U9 -> 150 | W9: 449
A10: Kurti sets | B10: 349 | C10: 130 | D10: =E10-C10 -> 245 | E10: 375 | F10: =G10-C10 -> 350 | G10: 480 | I10: Vest | J10: 111 | K10: 50 | L10: =M10-K10 -> 50 | M10: 100 | N10: =O10-K10 -> 99 | O10: 149 | Q10: Uniform - Men | R10: 699 - 899 | S10: 200 | T10: =U10-S10 -> 249 | U10: 449 | V10: =W10-U10 -> 230 | W10: 679
A11: Salwar / Anarkali suits | B11: 389 | C11: 180 | D11: =E11-C11 -> 389 | E11: 569 | F11: =G11-C11 -> 440 | G11: 620 | I11: Dhoti | J11: 110 | K11: 50 | L11: =M11-K11 -> 50 | M11: 100 | N11: =O11-K11 -> 99 | O11: 149 | Q11: Uniform - Women | R11: 399 - 899 | S11: 180 | T11: =U11-S11 -> 219 | U11: 399 | V11: =W11-U11 -> 200 | W11: 599
A12: Co-Ords / Fusions | B12: 326 | C12: 160 | D12: =E12-C12 -> 229 | E12: 389 | F12: =G12-C12 -> 323 | G12: 483 | I12: Kurta (Basic) | J12: 300 | K12: 120 | L12: =M12-K12 -> 159 | M12: 279 | N12: =O12-K12 -> 229 | O12: 349
A13: Leggings / Inskirts | B13: 127 | C13: 45 | D13: =E13-C13 -> 84 | E13: 129 | F13: =G13-C13 -> 152 | G13: 197 | I13: Kurta (Premium) | J13: 350 | K13: 140 | L13: =M13-K13 -> 319 | M13: 459 | N13: =O13-K13 -> 259 | O13: 399
A14: Skirt | B14: 149 | C14: 70 | D14: =E14-C14 -> 119 | E14: 189 | F14: =G14-C14 -> 229 | G14: 299 | I14: Sherwani (Basic) | J14: 480 | K14: 600 | L14: =M14-K14 -> 999 | M14: 1599 | N14: =O14-K14 -> 1299 | O14: 1899
A15: Blouse | B15: 250 | C15: 100 | D15: =E15-C15 -> 150 | E15: 250 | F15: =G15-C15 -> 210 | G15: 310 | I15: Sherwani (Premium) | J15: 600 | K15: 650 | L15: =M15-K15 -> 1450 | M15: 2100 | N15: =O15-K15 -> 1850 | O15: 2500
A16: Designer / Blouse | B16: 399 | C16: 200 | D16: =E16-C16 -> 250 | E16: 450 | F16: =G16-C16 -> 369 | G16: 569 | I16: Pant (Basic) | J16: 299 | K16: 130 | L16: =M16-K16 -> 250 | M16: 380 | N16: =O16-K16 -> 280 | O16: 410
A17: Innerwears | B17: 227 | C17: 80 | D17: =E17-C17 -> 130 | E17: 210 | F17: =G17-C17 -> 192 | G17: 272 | I17: Pant (Premium) | J17: 310 | K17: 130 | L17: =M17-K17 -> 320 | M17: 450 | N17: =O17-K17 -> 369 | O17: 499
A18: T-shirts | B18: 199 | C18: 70 | D18: =E18-C18 -> 98 | E18: 168 | F18: =G18-C18 -> 149 | G18: 219 | I18: Shot / Trousers (Basic) | J18: 199 | K18: 90 | L18: =M18-K18 -> 109 | M18: 199 | N18: =O18-K18 -> 149 | O18: 239
A19: Shots | B19: 199 | C19: 80 | D19: =E19-C19 -> 85 | E19: 165 | F19: =G19-C19 -> 169 | G19: 249 | I19: Shot / Trousers (Premium) | J19: 219 | K19: 100 | L19: =M19-K19 -> 135 | M19: 235 | N19: =O19-K19 -> 160 | O19: 260
A20: Trousers / Track pants | B20: 245 | C20: 100 | D20: =E20-C20 -> 130 | E20: 230 | F20: =G20-C20 -> 204 | G20: 304
A21: Formal Shirts & Pants set | B21: 499 | C21: 400 | D21: =E21-C21 -> 410 | E21: 810 | F21: =G21-C21 -> 600 | G21: 1000
A22: Nightwear / Loungewear | B22: 399 | C22: 100 | D22: =E22-C22 -> 169 | E22: 269 | F22: =G22-C22 -> 299 | G22: 399
A23: Lehanga Set | B23: 1099 | C23: 500 | D23: =E23-C23 -> 500 | E23: 1000 | F23: =G23-C23 -> 799 | G23: 1299
A24: Half Saree | B24: 999 | C24: 350 | D24: =E24-C24 -> 549 | E24: 899 | F24: =G24-C24 -> 649 | G24: 999
A32: EFFICIENT (16 - 50 prod) | I32: EFFICIENT (16 - 50 prod) | Q32: EFFICIENT (16 - 50 prod)
A34: WOMEN'S WEAR (Core , Ethnic , Western fusion / Nightwear) | I34: MEN'S WEAR (Core , Ethnic , Western fusion / Nightwear) | Q34: KID'S WEAR (Core , Ethnic , Western fusion / Nightwear)
A35: Category | B35: COS | C35: Tailor Cost | D35: Margin D2B | E35: D2B | F35: Margin D2C | G35: D2C | I35: Category | J35: COS | K35: Tailor Cost | L35: Margin D2B | M35: D2B | N35: Margin D2C | O35: D2C | Q35: Category | R35: COS | S35: Tailor Cost | T35: Margin D2B | U35: D2B | V35: Margin D2C | W35: D2C
A36: Short Kurti | B36: 136 | C36: 75 | D36: =E36 - C36 -> 80 | E36: =ROUND(E8*(1-8%),0) -> 155 | F36: =G36 - C36 -> 154.08 | G36: =G8 * (1-8%) -> 229.08 | I36: Shirt | J36: 233 | K36: 120 | L36: =M36 - K36 -> 110 | M36: =ROUND(M8*(1-8%),0) -> 230 | N36: =O36 - K36 -> 147 | O36: 267 | Q36: School Uniform(girls) | R36: 399 - 699 | S36: 120 | T36: =U36-S36 -> 183 | U36: =ROUND(U8 *(1 - 8%),0) -> 303 | V36: =W36 - S36 -> 339 | W36: =ROUND(W8 * (1 - 8%),0) -> 459
A37: Kurti | B37: 258 | C37: 90 | D37: =E37 - C37 -> 111 | E37: =ROUND(E9*(1-8%),0) -> 201 | F37: =G37 - C37 -> 221.88 | G37: =G9 * (1-8%) -> 311.88 | I37: T-Shirt | J37: 199 | K37: 70 | L37: =M37 - K37 -> 96 | M37: =ROUND(M9 * (1 - 8% ),0) -> 166 | N37: =O37 - K37 -> 86 | O37: 156 | Q37: School Uniform(Boys) | R37: 350 - 599 | S37: 110 | T37: =U37-S37 -> 165 | U37: =ROUND(U9 *(1 - 8%),0) -> 275 | V37: =W37 - S37 -> 303 | W37: =ROUND(W9 * (1 - 8%),0) -> 413
A38: Kurti sets | B38: 339 | C38: 130 | D38: =E38 - C38 -> 215 | E38: =ROUND(E10*(1-8%),0) -> 345 | F38: =G38 - C38 -> 311.6 | G38: =G10 * (1-8%) -> 441.6 | I38: Vest | J38: 111 | K38: 50 | L38: =M38 - K38 -> 42 | M38: =ROUND(M10 * (1 - 8% ),0) -> 92 | N38: =O38 - K38 -> 61 | O38: 111 | Q38: Uniform - Men | R38: 699 - 899 | S38: 200 | T38: =U38-S38 -> 213 | U38: =ROUND(U10 *(1 - 8%),0) -> 413 | V38: =W38 - S38 -> 425 | W38: =ROUND(W10 * (1 - 8%),0) -> 625
A39: Salwar / Anarkali suits | B39: 373 | C39: 180 | D39: =E39 - C39 -> 343 | E39: =ROUND(E11*(1-8%),0) -> 523 | F39: =G39 - C39 -> 390.4 | G39: =G11 * (1-8%) -> 570.4 | I39: Dhoti | J39: 110 | K39: 50 | L39: =M39 - K39 -> 42 | M39: =ROUND(M11 * (1 - 8% ),0) -> 92 | N39: =O39 - K39 -> 61 | O39: 111 | Q39: Uniform - Women | R39: 399 - 899 | S39: 180 | T39: =U39-S39 -> 187 | U39: =ROUND(U11 *(1 - 8%),0) -> 367 | V39: =W39 - S39 -> 371 | W39: =ROUND(W11 * (1 - 8%),0) -> 551
A40: Co-Ords / Fusions | B40: 317 | C40: 160 | D40: =E40 - C40 -> 198 | E40: =ROUND(E12*(1-8%),0) -> 358 | F40: =G40 - C40 -> 284.36 | G40: =G12 * (1-8%) -> 444.36 | I40: Kurta (Basic) | J40: 300 | K40: 120 | L40: =M40 - K40 -> 137 | M40: =ROUND(M12 * (1 - 8% ),0) -> 257 | N40: =O40 - K40 -> 147 | O40: 267
A41: Leggings / Inskirts | B41: 120 | C41: 45 | D41: =E41 - C41 -> 74 | E41: =ROUND(E13*(1-8%),0) -> 119 | F41: =G41 - C41 -> 136.24 | G41: =G13 * (1-8%) -> 181.24 | I41: Kurta (Premium) | J41: 350 | K41: 140 | L41: =M41 - K41 -> 282 | M41: =ROUND(M13 * (1 - 8% ),0) -> 422 | N41: =O41 - K41 -> 171 | O41: 311
A42: Skirt | B42: 139 | C42: 70 | D42: =E42 - C42 -> 104 | E42: =ROUND(E14*(1-8%),0) -> 174 | F42: =G42 - C42 -> 205.08 | G42: =G14 * (1-8%) -> 275.08 | I42: Sherwani (Basic) | J42: 480 | K42: 600 | L42: =M42 - K42 -> 871 | M42: =ROUND(M14 * (1 - 8% ),0) -> 1471 | N42: =O42 - K42 -> 733 | O42: 1333
A43: Blouse | B43: 179 | C43: 100 | D43: =E43 - C43 -> 130 | E43: =ROUND(E15*(1-8%),0) -> 230 | F43: =G43 - C43 -> 185.2 | G43: =G15 * (1-8%) -> 285.2 | I43: Sherwani (Premium) | J43: 600 | K43: 650 | L43: =M43 - K43 -> 1282 | M43: =ROUND(M15 * (1 - 8% ),0) -> 1932 | N43: =O43 - K43 -> 794 | O43: 1444
A44: Designer / Blouse | B44: 319 (basic) | C44: 200 | D44: =E44 - C44 -> 214 | E44: =ROUND(E16*(1-8%),0) -> 414 | F44: =G44 - C44 -> 323.48 | G44: =G16 * (1-8%) -> 523.48 | I44: Pant (Basic) | J44: 299 | K44: 130 | L44: =M44 - K44 -> 220 | M44: =ROUND(M16 * (1 - 8% ),0) -> 350 | N44: =O44 - K44 -> 159 | O44: 289
A45: Innerwears | B45: 217 | C45: 80 | D45: =E45 - C45 -> 113 | E45: =ROUND(E17*(1-8%),0) -> 193 | F45: =G45 - C45 -> 170.24 | G45: =G17 * (1-8%) -> 250.24 | I45: Pant (Premium) | J45: 310 | K45: 130 | L45: =M45 - K45 -> 284 | M45: =ROUND(M17 * (1 - 8% ),0) -> 414 | N45: =O45 - K45 -> 159 | O45: 289
A46: T-shirts | B46: 189 | C46: 70 | D46: =E46 - C46 -> 85 | E46: =ROUND(E18*(1-8%),0) -> 155 | F46: =G46 - C46 -> 131.48 | G46: =G18 * (1-8%) -> 201.48 | I46: Shot / Trousers (Basic) | J46: 199 | K46: 90 | L46: =M46 - K46 -> 93 | M46: =ROUND(M18 * (1 - 8% ),0) -> 183 | N46: =O46 - K46 -> 110 | O46: 200
A47: Shots | B47: 189 | C47: 80 | D47: =E47 - C47 -> 72 | E47: =ROUND(E19*(1-8%),0) -> 152 | F47: =G47 - C47 -> 149.08 | G47: =G19 * (1-8%) -> 229.08 | I47: Shot / Trousers (Premium) | J47: 219 | K47: 100 | L47: =M47 - K47 -> 116 | M47: =ROUND(M19 * (1 - 8% ),0) -> 216 | N47: =O47 - K47 -> 122 | O47: 222
A48: Trousers / Track pants | B48: 235 | C48: 100 | D48: =E48 - C48 -> 112 | E48: =ROUND(E20*(1-8%),0) -> 212 | F48: =G48 - C48 -> 179.68 | G48: =G20 * (1-8%) -> 279.68
A49: Formal Shirts and pants | B49: 489 | C49: 400 | D49: =E49 - C49 -> 345 | E49: =ROUND(E21*(1-8%),0) -> 745 | F49: =G49 - C49 -> 520 | G49: =G21 * (1-8%) -> 920
A50: Nightwear / Loungewear | B50: 383 | C50: 100 | D50: =E50 - C50 -> 147 | E50: =ROUND(E22*(1-8%),0) -> 247 | F50: =G50 - C50 -> 267.08 | G50: =G22 * (1-8%) -> 367.08
A51: Lehanga Set | B51: 1079 | C51: 500 | D51: =E51 - C51 -> 420 | E51: =ROUND(E23*(1-8%),0) -> 920 | F51: =G51 - C51 -> 695.08 | G51: =G23 * (1-8%) -> 1195.08
A52: Half Saree | B52: 993 | C52: 350 | D52: =E52 - C52 -> 477 | E52: =ROUND(E24*(1-8%),0) -> 827 | F52: =G52 - C52 -> 569.08 | G52: =G24 * (1-8%) -> 919.08
A55: PERIODIC (50 - 150+ prod) | I55: PERIODIC (50 - 150+ prod) | Q55: PERIODIC (50 - 150+ prod)
A57: WOMEN'S WEAR (Core , Ethnic , Western fusion / Nightwear) | I57: MEN'S WEAR (Core , Ethnic , Western fusion / Nightwear) | Q57: KID'S WEAR (Core , Ethnic , Western fusion / Nightwear)
A58: Category | B58: COS | C58: Tailor Cost | D58: Margin D2B | E58: D2B | F58: Margin D2C | G58: D2C | I58: Category | K58: Tailor Cost | L58: Margin D2B | M58: D2B | N58: Margin D2C | O58: D2C | Q58: Category | R58: COS | S58: Tailor Cost | T58: Margin | U58: D2B | V58: Margin | W58: D2C
A59: Short Kurti | B59: 157 | C59: 75 | D59: =E59 - C59 -> 68 | E59: =ROUND(E36 * (1 - 8%), 0) -> 143 | F59: =G59-C59 -> 136 | G59: =ROUND(G36 * (1 - 8%), 0) -> 211 | I59: Shirt | J59: 233 | K59: 120 | L59: =M59 - K59 -> 92 | M59: =ROUND(M36*(1 - 8%),0) -> 212 | N59: =O59 - K59 -> 126 | O59: =ROUND(O36 * (1 - 8%),0) -> 246 | Q59: School Uniform(girls) | R59: 399 - 699 | S59: 120 | T59: =U59 - S59 -> 159 | U59: =ROUND(U36 * (1 - 8%),0) -> 279 | V59: =W59-S59 -> 302 | W59: =ROUND(W36 * (1 - 8%), 0) -> 422
A60: Kurti | B60: 247 | C60: 90 | D60: =E60 - C60 -> 95 | E60: =ROUND(E37 * (1 - 8%), 0) -> 185 | F60: =G60-C60 -> 197 | G60: =ROUND(G37 * (1 - 8%), 0) -> 287 | I60: T-Shirt | J60: 199 | K60: 70 | L60: =M60 - K60 -> 83 | M60: =ROUND(M37*(1 - 8%),0) -> 153 | N60: =O60 - K60 -> 74 | O60: =ROUND(O37 * (1 - 8%),0) -> 144 | Q60: School Uniform(Boys) | R60: 350 - 599 | S60: 110 | T60: =U60 - S60 -> 143 | U60: =ROUND(U37 * (1 - 8%),0) -> 253 | V60: =W60-S60 -> 270 | W60: =ROUND(W37 * (1 - 8%), 0) -> 380
A61: Kurti sets | B61: 329 | C61: 130 | D61: =E61 - C61 -> 187 | E61: =ROUND(E38 * (1 - 8%), 0) -> 317 | F61: =G61-C61 -> 276 | G61: =ROUND(G38 * (1 - 8%), 0) -> 406 | I61: Vest | J61: 111 | K61: 50 | L61: =M61 - K61 -> 35 | M61: =ROUND(M38*(1 - 8%),0) -> 85 | N61: =O61 - K61 -> 52 | O61: =ROUND(O38 * (1 - 8%),0) -> 102 | Q61: Uniform - Men | R61: 699 - 899 | S61: 200 | T61: =U61 - S61 -> 180 | U61: =ROUND(U38 * (1 - 8%),0) -> 380 | V61: =W61-S61 -> 375 | W61: =ROUND(W38 * (1 - 8%), 0) -> 575
A62: Salwar / Anarkali suits | B62: 367 | C62: 180 | D62: =E62 - C62 -> 301 | E62: =ROUND(E39 * (1 - 8%), 0) -> 481 | F62: =G62-C62 -> 345 | G62: =ROUND(G39 * (1 - 8%), 0) -> 525 | I62: Dhoti | J62: 110 | K62: 50 | L62: =M62 - K62 -> 35 | M62: =ROUND(M39*(1 - 8%),0) -> 85 | N62: =O62 - K62 -> 52 | O62: =ROUND(O39 * (1 - 8%),0) -> 102 | Q62: Uniform - Women | R62: 399 - 899 | S62: 180 | T62: =U62 - S62 -> 158 | U62: =ROUND(U39 * (1 - 8%),0) -> 338 | V62: =W62-S62 -> 327 | W62: =ROUND(W39 * (1 - 8%), 0) -> 507
A63: Co-Ords / Fusions | B63: 309 | C63: 160 | D63: =E63 - C63 -> 169 | E63: =ROUND(E40 * (1 - 8%), 0) -> 329 | F63: =G63-C63 -> 249 | G63: =ROUND(G40 * (1 - 8%), 0) -> 409 | I63: Kurta (Basic) | J63: 300 | K63: 120 | L63: =M63 - K63 -> 116 | M63: =ROUND(M40*(1 - 8%),0) -> 236 | N63: =O63 - K63 -> 126 | O63: =ROUND(O40 * (1 - 8%),0) -> 246
A64: Leggings / Inskirts | B64: 101 | C64: 45 | D64: =E64 - C64 -> 64 | E64: =ROUND(E41 * (1 - 8%), 0) -> 109 | F64: =G64-C64 -> 122 | G64: =ROUND(G41 * (1 - 8%), 0) -> 167 | I64: Kurta (Premium) | J64: 350 | K64: 140 | L64: =M64 - K64 -> 248 | M64: =ROUND(M41*(1 - 8%),0) -> 388 | N64: =O64 - K64 -> 146 | O64: =ROUND(O41 * (1 - 8%),0) -> 286
A65: Skirt | B65: 132 | C65: 70 | D65: =E65 - C65 -> 90 | E65: =ROUND(E42 * (1 - 8%), 0) -> 160 | F65: =G65-C65 -> 183 | G65: =ROUND(G42 * (1 - 8%), 0) -> 253 | I65: Sherwani (Basic) | J65: 480 | K65: 600 | L65: =M65 - K65 -> 753 | M65: =ROUND(M42*(1 - 8%),0) -> 1353 | N65: =O65 - K65 -> 626 | O65: =ROUND(O42 * (1 - 8%),0) -> 1226
A66: Blouse | B66: 174 | C66: 100 | D66: =E66 - C66 -> 112 | E66: =ROUND(E43 * (1 - 8%), 0) -> 212 | F66: =G66-C66 -> 162 | G66: =ROUND(G43 * (1 - 8%), 0) -> 262 | I66: Sherwani (Premium) | J66: 600 | K66: 650 | L66: =M66 - K66 -> 1127 | M66: =ROUND(M43*(1 - 8%),0) -> 1777 | N66: =O66 - K66 -> 678 | O66: =ROUND(O43 * (1 - 8%),0) -> 1328
A67: Designer / Blouse | B67: 309 (basic) | C67: 200 | D67: =E67 - C67 -> 181 | E67: =ROUND(E44 * (1 - 8%), 0) -> 381 | F67: =G67-C67 -> 282 | G67: =ROUND(G44 * (1 - 8%), 0) -> 482 | I67: Pant (Basic) | J67: 299 | K67: 130 | L67: =M67 - K67 -> 192 | M67: =ROUND(M44*(1 - 8%),0) -> 322 | N67: =O67 - K67 -> 136 | O67: =ROUND(O44 * (1 - 8%),0) -> 266
A68: Innerwears | B68: 211 | C68: 80 | D68: =E68 - C68 -> 98 | E68: =ROUND(E45 * (1 - 8%), 0) -> 178 | F68: =G68-C68 -> 150 | G68: =ROUND(G45 * (1 - 8%), 0) -> 230 | I68: Pant (Premium) | J68: 310 | K68: 130 | L68: =M68 - K68 -> 251 | M68: =ROUND(M45*(1 - 8%),0) -> 381 | N68: =O68 - K68 -> 136 | O68: =ROUND(O45 * (1 - 8%),0) -> 266
A69: T-shirts | B69: 182 | C69: 70 | D69: =E69 - C69 -> 73 | E69: =ROUND(E46 * (1 - 8%), 0) -> 143 | F69: =G69-C69 -> 115 | G69: =ROUND(G46 * (1 - 8%), 0) -> 185 | I69: Shot / Trousers (Basic) | J69: 199 | K69: 90 | L69: =M69 - K69 -> 78 | M69: =ROUND(M46*(1 - 8%),0) -> 168 | N69: =O69 - K69 -> 94 | O69: =ROUND(O46 * (1 - 8%),0) -> 184
A70: Shots | B70: 181 | C70: 80 | D70: =E70 - C70 -> 60 | E70: =ROUND(E47 * (1 - 8%), 0) -> 140 | F70: =G70-C70 -> 131 | G70: =ROUND(G47 * (1 - 8%), 0) -> 211 | I70: Shot / Trousers (Premium) | J70: 219 | K70: 100 | L70: =M70 - K70 -> 99 | M70: =ROUND(M47*(1 - 8%),0) -> 199 | N70: =O70 - K70 -> 104 | O70: =ROUND(O47 * (1 - 8%),0) -> 204
A71: Trousers / Track pants | B71: 229 | C71: 100 | D71: =E71 - C71 -> 95 | E71: =ROUND(E48 * (1 - 8%), 0) -> 195 | F71: =G71-C71 -> 157 | G71: =ROUND(G48 * (1 - 8%), 0) -> 257
A72: Formal Shirts & Pants set | B72: 480 | C72: 200 | D72: =E72 - C72 -> 485 | E72: =ROUND(E49 * (1 - 8%), 0) -> 685 | F72: =G72-C72 -> 646 | G72: =ROUND(G49 * (1 - 8%), 0) -> 846
A73: Nightwear / Loungewear | B73: 380 | C73: 100 | D73: =E73 - C73 -> 127 | E73: =ROUND(E50 * (1 - 8%), 0) -> 227 | F73: =G73-C73 -> 238 | G73: =ROUND(G50 * (1 - 8%), 0) -> 338
A74: Lehanga Set | B74: 1066 | C74: 500 | D74: =E74 - C74 -> 346 | E74: =ROUND(E51 * (1 - 8%), 0) -> 846 | F74: =G74-C74 -> 599 | G74: =ROUND(G51 * (1 - 8%), 0) -> 1099
A75: Half Saree | B75: 989 | C75: 350 | D75: =E75 - C75 -> 411 | E75: =ROUND(E52 * (1 - 8%), 0) -> 761 | F75: =G75-C75 -> 496 | G75: =ROUND(G52 * (1 - 8%), 0) -> 846

Sheet tailor cost
A2: Women's Wear (60 % margin ) | D2: Men's Wear (60 % margin ) | G2: Kid 's Wear & uniforms (60 % margin )
A4: Category | B4: Tailor Cost | D4: Category | E4: Tailor Cost | G4: Category | H4: Tailor Cost
A5: Short Kurti | B5: 75 | D5: Shirt | E5: 120 | G5: School Uniform(girls) | H5: 120
A6: Kurti | B6: 90 | D6: T-Shirt | E6: 80 | G6: School Uniform(Boys) | H6: 110
A7: Kurti sets | B7: 130 | D7: Vest | E7: 50 | G7: Uniform - Men | H7: 200
A8: Salwar / Anarkali suits | B8: 180 | D8: Dhoti | E8: 50 | G8: Uniform - Women | H8: 180
A9: Co-Ords / Fusions | B9: 160 | D9: Kurta (Basic) | E9: 120
A10: Leggings / Inskirts | B10: 45 | D10: Kurta (Premium) | E10: 140
A11: Skirt | B11: 70 | D11: Sherwani (Basic) | E11: 600
A12: Blouse | B12: 100 | D12: Sherwani (Premium) | E12: 650
A13: Designer / Blouse | B13: 200 | D13: Pant (Basic) | E13: 130
A14: Innerwears | B14: 80 | D14: Pant (Premium) | E14: 130
A15: T-shirts | B15: 70 | D15: Shot / Trousers (Basic) | E15: 90 | G15: Product Lot - 50 products (MAX)
A16: Shots | B16: 80 | D16: Shot / Trousers (Premium) | E16: 100
A17: Trousers / Track pants | B17: 100
A18: Formal Shirts & Pants set | B18: 400
A19: Nightwear / Loungewear | B19: 100
A20: Lehanga Set | B20: 500
A21: Half Saree | B21: 350

Sheet analysis
F2: Min Margin % | L2: Min Margin % | R2: Min Margin % | X2: Min Margin % | AE2: Min Margin % | AK2: Min Margin %
F3: 0.5 | L3: 0.6 | R3: 0.5 | X3: 0.6 | AE3: 0.5 | AK3: 0.6
C5: Category | D5: Profit Margin B2B | E5: Actual sale Price | G5: Price Change Required | I5: Category | J5: Profit Margin B2C | K5: Actual sale Price | M5: Price Change Required | O5: Category | P5: Profit Margin B2B | Q5: Actual sale Price | S5: Price Change Required | U5: Category | V5: Profit Margin B2C | W5: Actual sale Price | Y5: Price Change Required | AB5: Category | AC5: Profit Margin B2B | AD5: Actual sale Price | AF5: Price Change Required | AH5: Category | AI5: Profit Margin B2C | AJ5: Actual sale Price | AL5: Price Change Required
C6: =pricing_chart!A8 -> Short Kurti | D6: =pricing_chart!D8/pricing_chart!E8 -> 0.55621302 | E6: =pricing_chart!E8 -> 169 | F6: =pricing_chart!C8/(1-analysis!$F$3) -> 150 | G6: =IF(F6<E6,0,F6-E6) -> 0 | I6: =pricing_chart!A8 -> Short Kurti | J6: =pricing_chart!F8/pricing_chart!G8 -> 0.69879518 | K6: =pricing_chart!G8 -> 249 | L6: =pricing_chart!C8/(1-analysis!$L$3) -> 187.5 | M6: =IF(L6<K6,0,L6-K6) -> 0 | O6: =pricing_chart!I8 -> Shirt | P6: =pricing_chart!L8/pricing_chart!M8 -> 0.52 | Q6: =pricing_chart!M8 -> 250 | R6: =pricing_chart!K8/(1-analysis!$R$3) -> 240 | S6: =IF(R6<Q6,0,R6-Q6) -> 0 | U6: =pricing_chart!I8 -> Shirt | V6: =pricing_chart!N8/pricing_chart!O8 -> 0.6 | W6: =pricing_chart!O8 -> 300 | X6: =pricing_chart!K8/(1-analysis!$X$3) -> 300 | Y6: =IF(X6<W6,0,X6-W6) -> 0 | AB6: =pricing_chart!Q8 -> School Uniform(girls) | AC6: =pricing_chart!T8/pricing_chart!U8 -> 0.63525836 | AD6: =pricing_chart!U8 -> 329 | AE6: =pricing_chart!S8/(1-analysis!$AE$3) -> 240 | AF6: =IF(AE6<AD6,0,AE6-AD6) -> 0 | AH6: =pricing_chart!Q8 -> School Uniform(girls) | AI6: =pricing_chart!V8/pricing_chart!W8 -> 0.34068136 | AJ6: =pricing_chart!W8 -> 499 | AK6: =(pricing_chart!S8/(1-analysis!$AK$3)) -> 300 | AL6: =IF(AK6<AJ6,0,AK6-AJ6) -> 0
C7: =pricing_chart!A9 -> Kurti | D7: =pricing_chart!D9/pricing_chart!E9 -> 0.5890411 | E7: =pricing_chart!E9 -> 219 | F7: =pricing_chart!C9/(1-analysis!$F$3) -> 180 | G7: =IF(F7<E7,0,F7-E7) -> 0 | I7: =pricing_chart!A9 -> Kurti | J7: =pricing_chart!F9/pricing_chart!G9 -> 0.73451327 | K7: =pricing_chart!G9 -> 339 | L7: =pricing_chart!C9/(1-analysis!$L$3) -> 225 | M7: =IF(L7<K7,0,L7-K7) -> 0 | O7: =pricing_chart!I9 -> T-Shirt | P7: =pricing_chart!L9/pricing_chart!M9 -> 0.55555556 | Q7: =pricing_chart!M9 -> 180 | R7: =pricing_chart!K9/(1-analysis!$R$3) -> 160 | S7: =IF(R7<Q7,0,R7-Q7) -> 0 | U7: =pricing_chart!I9 -> T-Shirt | V7: =pricing_chart!N9/pricing_chart!O9 -> 0.63636364 | W7: =pricing_chart!O9 -> 220 | X7: =pricing_chart!K9/(1-analysis!$X$3) -> 200 | Y7: =IF(X7<W7,0,X7-W7) -> 0 | AB7: =pricing_chart!Q9 -> School Uniform(Boys) | AC7: =pricing_chart!T9/pricing_chart!U9 -> 0.63210702 | AD7: =pricing_chart!U9 -> 299 | AE7: =pricing_chart!S9/(1-analysis!$AE$3) -> 220 | AF7: =IF(AE7<AD7,0,AE7-AD7) -> 0 | AH7: =pricing_chart!Q9 -> School Uniform(Boys) | AI7: =pricing_chart!V9/pricing_chart!W9 -> 0.33407572 | AJ7: =pricing_chart!W9 -> 449 | AK7: =(pricing_chart!S9/(1-analysis!$AK$3)) -> 275 | AL7: =IF(AK7<AJ7,0,AK7-AJ7) -> 0
C8: =pricing_chart!A10 -> Kurti sets | D8: =pricing_chart!D10/pricing_chart!E10 -> 0.65333333 | E8: =pricing_chart!E10 -> 375 | F8: =pricing_chart!C10/(1-analysis!$F$3) -> 260 | G8: =IF(F8<E8,0,F8-E8) -> 0 | I8: =pricing_chart!A10 -> Kurti sets | J8: =pricing_chart!F10/pricing_chart!G10 -> 0.72916667 | K8: =pricing_chart!G10 -> 480 | L8: =pricing_chart!C10/(1-analysis!$L$3) -> 325 | M8: =IF(L8<K8,0,L8-K8) -> 0 | O8: =pricing_chart!I10 -> Vest | P8: =pricing_chart!L10/pricing_chart!M10 -> 0.5 | Q8: =pricing_chart!M10 -> 100 | R8: =pricing_chart!K10/(1-analysis!$R$3) -> 100 | S8: =IF(R8<Q8,0,R8-Q8) -> 0 | U8: =pricing_chart!I10 -> Vest | V8: =pricing_chart!N10/pricing_chart!O10 -> 0.66442953 | W8: =pricing_chart!O10 -> 149 | X8: =pricing_chart!K10/(1-analysis!$X$3) -> 125 | Y8: =IF(X8<W8,0,X8-W8) -> 0 | AB8: =pricing_chart!Q10 -> Uniform - Men | AC8: =pricing_chart!T10/pricing_chart!U10 -> 0.5545657 | AD8: =pricing_chart!U10 -> 449 | AE8: =pricing_chart!S10/(1-analysis!$AE$3) -> 400 | AF8: =IF(AE8<AD8,0,AE8-AD8) -> 0 | AH8: =pricing_chart!Q10 -> Uniform - Men | AI8: =pricing_chart!V10/pricing_chart!W10 -> 0.33873343 | AJ8: =pricing_chart!W10 -> 679 | AK8: =(pricing_chart!S10/(1-analysis!$AK$3)) -> 500 | AL8: =IF(AK8<AJ8,0,AK8-AJ8) -> 0
C9: =pricing_chart!A11 -> Salwar / Anarkali suits | D9: =pricing_chart!D11/pricing_chart!E11 -> 0.68365554 | E9: =pricing_chart!E11 -> 569 | F9: =pricing_chart!C11/(1-analysis!$F$3) -> 360 | G9: =IF(F9<E9,0,F9-E9) -> 0 | I9: =pricing_chart!A11 -> Salwar / Anarkali suits | J9: =pricing_chart!F11/pricing_chart!G11 -> 0.70967742 | K9: =pricing_chart!G11 -> 620 | L9: =pricing_chart!C11/(1-analysis!$L$3) -> 450 | M9: =IF(L9<K9,0,L9-K9) -> 0 | O9: =pricing_chart!I11 -> Dhoti | P9: =pricing_chart!L11/pricing_chart!M11 -> 0.5 | Q9: =pricing_chart!M11 -> 100 | R9: =pricing_chart!K11/(1-analysis!$R$3) -> 100 | S9: =IF(R9<Q9,0,R9-Q9) -> 0 | U9: =pricing_chart!I11 -> Dhoti | V9: =pricing_chart!N11/pricing_chart!O11 -> 0.66442953 | W9: =pricing_chart!O11 -> 149 | X9: =pricing_chart!K11/(1-analysis!$X$3) -> 125 | Y9: =IF(X9<W9,0,X9-W9) -> 0 | AB9: =pricing_chart!Q11 -> Uniform - Women | AC9: =pricing_chart!T11/pricing_chart!U11 -> 0.54887218 | AD9: =pricing_chart!U11 -> 399 | AE9: =pricing_chart!S11/(1-analysis!$AE$3) -> 360 | AF9: =IF(AE9<AD9,0,AE9-AD9) -> 0 | AH9: =pricing_chart!Q11 -> Uniform - Women | AI9: =pricing_chart!V11/pricing_chart!W11 -> 0.33388982 | AJ9: =pricing_chart!W11 -> 599 | AK9: =(pricing_chart!S11/(1-analysis!$AK$3)) -> 450 | AL9: =IF(AK9<AJ9,0,AK9-AJ9) -> 0
C10: =pricing_chart!A12 -> Co-Ords / Fusions | D10: =pricing_chart!D12/pricing_chart!E12 -> 0.58868895 | E10: =pricing_chart!E12 -> 389 | F10: =pricing_chart!C12/(1-analysis!$F$3) -> 320 | G10: =IF(F10<E10,0,F10-E10) -> 0 | I10: =pricing_chart!A12 -> Co-Ords / Fusions | J10: =pricing_chart!F12/pricing_chart!G12 -> 0.66873706 | K10: =pricing_chart!G12 -> 483 | L10: =pricing_chart!C12/(1-analysis!$L$3) -> 400 | M10: =IF(L10<K10,0,L10-K10) -> 0 | O10: =pricing_chart!I12 -> Kurta (Basic) | P10: =pricing_chart!L12/pricing_chart!M12 -> 0.56989247 | Q10: =pricing_chart!M12 -> 279 | R10: =pricing_chart!K12/(1-analysis!$R$3) -> 240 | S10: =IF(R10<Q10,0,R10-Q10) -> 0 | U10: =pricing_chart!I12 -> Kurta (Basic) | V10: =pricing_chart!N12/pricing_chart!O12 -> 0.65616046 | W10: =pricing_chart!O12 -> 349 | X10: =pricing_chart!K12/(1-analysis!$X$3) -> 300 | Y10: =IF(X10<W10,0,X10-W10) -> 0
C11: =pricing_chart!A13 -> Leggings / Inskirts | D11: =pricing_chart!D13/pricing_chart!E13 -> 0.65116279 | E11: =pricing_chart!E13 -> 129 | F11: =pricing_chart!C13/(1-analysis!$F$3) -> 90 | G11: =IF(F11<E11,0,F11-E11) -> 0 | I11: =pricing_chart!A13 -> Leggings / Inskirts | J11: =pricing_chart!F13/pricing_chart!G13 -> 0.7715736 | K11: =pricing_chart!G13 -> 197 | L11: =pricing_chart!C13/(1-analysis!$L$3) -> 112.5 | M11: =IF(L11<K11,0,L11-K11) -> 0 | O11: =pricing_chart!I13 -> Kurta (Premium) | P11: =pricing_chart!L13/pricing_chart!M13 -> 0.69498911 | Q11: =pricing_chart!M13 -> 459 | R11: =pricing_chart!K13/(1-analysis!$R$3) -> 280 | S11: =IF(R11<Q11,0,R11-Q11) -> 0 | U11: =pricing_chart!I13 -> Kurta (Premium) | V11: =pricing_chart!N13/pricing_chart!O13 -> 0.64912281 | W11: =pricing_chart!O13 -> 399 | X11: =pricing_chart!K13/(1-analysis!$X$3) -> 350 | Y11: =IF(X11<W11,0,X11-W11) -> 0
C12: =pricing_chart!A14 -> Skirt | D12: =pricing_chart!D14/pricing_chart!E14 -> 0.62962963 | E12: =pricing_chart!E14 -> 189 | F12: =pricing_chart!C14/(1-analysis!$F$3) -> 140 | G12: =IF(F12<E12,0,F12-E12) -> 0 | I12: =pricing_chart!A14 -> Skirt | J12: =pricing_chart!F14/pricing_chart!G14 -> 0.76588629 | K12: =pricing_chart!G14 -> 299 | L12: =pricing_chart!C14/(1-analysis!$L$3) -> 175 | M12: =IF(L12<K12,0,L12-K12) -> 0 | O12: =pricing_chart!I14 -> Sherwani (Basic) | P12: =pricing_chart!L14/pricing_chart!M14 -> 0.62476548 | Q12: =pricing_chart!M14 -> 1599 | R12: =pricing_chart!K14/(1-analysis!$R$3) -> 1200 | S12: =IF(R12<Q12,0,R12-Q12) -> 0 | U12: =pricing_chart!I14 -> Sherwani (Basic) | V12: =pricing_chart!N14/pricing_chart!O14 -> 0.68404423 | W12: =pricing_chart!O14 -> 1899 | X12: =pricing_chart!K14/(1-analysis!$X$3) -> 1500 | Y12: =IF(X12<W12,0,X12-W12) -> 0
C13: =pricing_chart!A15 -> Blouse | D13: =pricing_chart!D15/pricing_chart!E15 -> 0.6 | E13: =pricing_chart!E15 -> 250 | F13: =pricing_chart!C15/(1-analysis!$F$3) -> 200 | G13: =IF(F13<E13,0,F13-E13) -> 0 | I13: =pricing_chart!A15 -> Blouse | J13: =pricing_chart!F15/pricing_chart!G15 -> 0.67741935 | K13: =pricing_chart!G15 -> 310 | L13: =pricing_chart!C15/(1-analysis!$L$3) -> 250 | M13: =IF(L13<K13,0,L13-K13) -> 0 | O13: =pricing_chart!I15 -> Sherwani (Premium) | P13: =pricing_chart!L15/pricing_chart!M15 -> 0.69047619 | Q13: =pricing_chart!M15 -> 2100 | R13: =pricing_chart!K15/(1-analysis!$R$3) -> 1300 | S13: =IF(R13<Q13,0,R13-Q13) -> 0 | U13: =pricing_chart!I15 -> Sherwani (Premium) | V13: =pricing_chart!N15/pricing_chart!O15 -> 0.74 | W13: =pricing_chart!O15 -> 2500 | X13: =pricing_chart!K15/(1-analysis!$X$3) -> 1625 | Y13: =IF(X13<W13,0,X13-W13) -> 0
C14: =pricing_chart!A16 -> Designer / Blouse | D14: =pricing_chart!D16/pricing_chart!E16 -> 0.55555556 | E14: =pricing_chart!E16 -> 450 | F14: =pricing_chart!C16/(1-analysis!$F$3) -> 400 | G14: =IF(F14<E14,0,F14-E14) -> 0 | I14: =pricing_chart!A16 -> Designer / Blouse | J14: =pricing_chart!F16/pricing_chart!G16 -> 0.64850615 | K14: =pricing_chart!G16 -> 569 | L14: =pricing_chart!C16/(1-analysis!$L$3) -> 500 | M14: =IF(L14<K14,0,L14-K14) -> 0 | O14: =pricing_chart!I16 -> Pant (Basic) | P14: =pricing_chart!L16/pricing_chart!M16 -> 0.65789474 | Q14: =pricing_chart!M16 -> 380 | R14: =pricing_chart!K16/(1-analysis!$R$3) -> 260 | S14: =IF(R14<Q14,0,R14-Q14) -> 0 | U14: =pricing_chart!I16 -> Pant (Basic) | V14: =pricing_chart!N16/pricing_chart!O16 -> 0.68292683 | W14: =pricing_chart!O16 -> 410 | X14: =pricing_chart!K16/(1-analysis!$X$3) -> 325 | Y14: =IF(X14<W14,0,X14-W14) -> 0
C15: =pricing_chart!A17 -> Innerwears | D15: =pricing_chart!D17/pricing_chart!E17 -> 0.61904762 | E15: =pricing_chart!E17 -> 210 | F15: =pricing_chart!C17/(1-analysis!$F$3) -> 160 | G15: =IF(F15<E15,0,F15-E15) -> 0 | I15: =pricing_chart!A17 -> Innerwears | J15: =pricing_chart!F17/pricing_chart!G17 -> 0.70588235 | K15: =pricing_chart!G17 -> 272 | L15: =pricing_chart!C17/(1-analysis!$L$3) -> 200 | M15: =IF(L15<K15,0,L15-K15) -> 0 | O15: =pricing_chart!I17 -> Pant (Premium) | P15: =pricing_chart!L17/pricing_chart!M17 -> 0.71111111 | Q15: =pricing_chart!M17 -> 450 | R15: =pricing_chart!K17/(1-analysis!$R$3) -> 260 | S15: =IF(R15<Q15,0,R15-Q15) -> 0 | U15: =pricing_chart!I17 -> Pant (Premium) | V15: =pricing_chart!N17/pricing_chart!O17 -> 0.73947896 | W15: =pricing_chart!O17 -> 499 | X15: =pricing_chart!K17/(1-analysis!$X$3) -> 325 | Y15: =IF(X15<W15,0,X15-W15) -> 0
C16: =pricing_chart!A18 -> T-shirts | D16: =pricing_chart!D18/pricing_chart!E18 -> 0.58333333 | E16: =pricing_chart!E18 -> 168 | F16: =pricing_chart!C18/(1-analysis!$F$3) -> 140 | G16: =IF(F16<E16,0,F16-E16) -> 0 | I16: =pricing_chart!A18 -> T-shirts | J16: =pricing_chart!F18/pricing_chart!G18 -> 0.6803653 | K16: =pricing_chart!G18 -> 219 | L16: =pricing_chart!C18/(1-analysis!$L$3) -> 175 | M16: =IF(L16<K16,0,L16-K16) -> 0 | O16: =pricing_chart!I18 -> Shot / Trousers (Basic) | P16: =pricing_chart!L18/pricing_chart!M18 -> 0.54773869 | Q16: =pricing_chart!M18 -> 199 | R16: =pricing_chart!K18/(1-analysis!$R$3) -> 180 | S16: =IF(R16<Q16,0,R16-Q16) -> 0 | U16: =pricing_chart!I18 -> Shot / Trousers (Basic) | V16: =pricing_chart!N18/pricing_chart!O18 -> 0.62343096 | W16: =pricing_chart!O18 -> 239 | X16: =pricing_chart!K18/(1-analysis!$X$3) -> 225 | Y16: =IF(X16<W16,0,X16-W16) -> 0
C17: =pricing_chart!A19 -> Shots | D17: =pricing_chart!D19/pricing_chart!E19 -> 0.51515152 | E17: =pricing_chart!E19 -> 165 | F17: =pricing_chart!C19/(1-analysis!$F$3) -> 160 | G17: =IF(F17<E17,0,F17-E17) -> 0 | I17: =pricing_chart!A19 -> Shots | J17: =pricing_chart!F19/pricing_chart!G19 -> 0.67871486 | K17: =pricing_chart!G19 -> 249 | L17: =pricing_chart!C19/(1-analysis!$L$3) -> 200 | M17: =IF(L17<K17,0,L17-K17) -> 0 | O17: =pricing_chart!I19 -> Shot / Trousers (Premium) | P17: =pricing_chart!L19/pricing_chart!M19 -> 0.57446809 | Q17: =pricing_chart!M19 -> 235 | R17: =pricing_chart!K19/(1-analysis!$R$3) -> 200 | S17: =IF(R17<Q17,0,R17-Q17) -> 0 | U17: =pricing_chart!I19 -> Shot / Trousers (Premium) | V17: =pricing_chart!N19/pricing_chart!O19 -> 0.61538462 | W17: =pricing_chart!O19 -> 260 | X17: =pricing_chart!K19/(1-analysis!$X$3) -> 250 | Y17: =IF(X17<W17,0,X17-W17) -> 0
C18: =pricing_chart!A20 -> Trousers / Track pants | D18: =pricing_chart!D20/pricing_chart!E20 -> 0.56521739 | E18: =pricing_chart!E20 -> 230 | F18: =pricing_chart!C20/(1-analysis!$F$3) -> 200 | G18: =IF(F18<E18,0,F18-E18) -> 0 | I18: =pricing_chart!A20 -> Trousers / Track pants | J18: =pricing_chart!F20/pricing_chart!G20 -> 0.67105263 | K18: =pricing_chart!G20 -> 304 | L18: =pricing_chart!C20/(1-analysis!$L$3) -> 250 | M18: =IF(L18<K18,0,L18-K18) -> 0
C19: =pricing_chart!A21 -> Formal Shirts & Pants set | D19: =pricing_chart!D21/pricing_chart!E21 -> 0.50617284 | E19: =pricing_chart!E21 -> 810 | F19: =pricing_chart!C21/(1-analysis!$F$3) -> 800 | G19: =IF(F19<E19,0,F19-E19) -> 0 | I19: =pricing_chart!A21 -> Formal Shirts & Pants set | J19: =pricing_chart!F21/pricing_chart!G21 -> 0.6 | K19: =pricing_chart!G21 -> 1000 | L19: =pricing_chart!C21/(1-analysis!$L$3) -> 1000 | M19: =IF(L19<K19,0,L19-K19) -> 0
C20: =pricing_chart!A22 -> Nightwear / Loungewear | D20: =pricing_chart!D22/pricing_chart!E22 -> 0.62825279 | E20: =pricing_chart!E22 -> 269 | F20: =pricing_chart!C22/(1-analysis!$F$3) -> 200 | G20: =IF(F20<E20,0,F20-E20) -> 0 | I20: =pricing_chart!A22 -> Nightwear / Loungewear | J20: =pricing_chart!F22/pricing_chart!G22 -> 0.74937343 | K20: =pricing_chart!G22 -> 399 | L20: =pricing_chart!C22/(1-analysis!$L$3) -> 250 | M20: =IF(L20<K20,0,L20-K20) -> 0
C21: =pricing_chart!A23 -> Lehanga Set | D21: =pricing_chart!D23/pricing_chart!E23 -> 0.5 | E21: =pricing_chart!E23 -> 1000 | F21: =pricing_chart!C23/(1-analysis!$F$3) -> 1000 | G21: =IF(F21<E21,0,F21-E21) -> 0 | I21: =pricing_chart!A23 -> Lehanga Set | J21: =pricing_chart!F23/pricing_chart!G23 -> 0.61508853 | K21: =pricing_chart!G23 -> 1299 | L21: =pricing_chart!C23/(1-analysis!$L$3) -> 1250 | M21: =IF(L21<K21,0,L21-K21) -> 0
C22: =pricing_chart!A24 -> Half Saree | D22: =pricing_chart!D24/pricing_chart!E24 -> 0.61067853 | E22: =pricing_chart!E24 -> 899 | F22: =pricing_chart!C24/(1-analysis!$F$3) -> 700 | G22: =IF(F22<E22,0,F22-E22) -> 0 | I22: =pricing_chart!A24 -> Half Saree | J22: =pricing_chart!F24/pricing_chart!G24 -> 0.64964965 | K22: =pricing_chart!G24 -> 999 | L22: =pricing_chart!C24/(1-analysis!$L$3) -> 875 | M22: =IF(L22<K22,0,L22-K22) -> 0
F25: Min Margin % | L25: Min Margin % | R25: Min Margin % | X25: Min Margin % | AE25: Min Margin % | AK25: Min Margin %
F26: 0.5 | L26: 0.5 | R26: 0.5 | X26: 0.55 | AE26: 0.6 | AK26: 0.55
C28: Category | D28: Profit Margin B2B | E28: Actual sale Price | G28: Price Change Required | I28: Category | J28: Profit Margin B2C | K28: Actual sale Price | M28: Price Change Required | O28: Category | P28: Profit Margin B2B | Q28: Actual sale Price | S28: Price Change Required | U28: Category | V28: Profit Margin B2C | W28: Actual sale Price | Y28: Price Change Required | AB28: Category | AC28: Profit Margin B2B | AD28: Actual sale Price | AF28: Price Change Required | AH28: Category | AI28: Profit Margin B2C | AJ28: Actual sale Price | AL28: Price Change Required
C29: =C6 -> Short Kurti | D29: =pricing_chart!D36/pricing_chart!E36 -> 0.51612903 | E29: =pricing_chart!E36 -> 155 | F29: =pricing_chart!C36/(1-analysis!$F$26) -> 150 | G29: =IF(F29<E29,0,F29-E29) -> 0 | I29: =I6 -> Short Kurti | J29: =pricing_chart!F36/pricing_chart!G36 -> 0.67260346 | K29: =pricing_chart!G36 -> 229.08 | L29: =pricing_chart!C36/(1-analysis!$L$26) -> 150 | M29: =IF(L29<K29,0,L29-K29) -> 0 | O29: =O6 -> Shirt | P29: =pricing_chart!L36/pricing_chart!M36 -> 0.47826087 | Q29: =pricing_chart!M36 -> 230 | R29: =pricing_chart!K36/(1-analysis!$R$26) -> 240 | S29: =IF(R29<Q29,0,R29-Q29) -> 10 | U29: =U6 -> Shirt | V29: =pricing_chart!N36/pricing_chart!O36 -> 0.5505618 | W29: =pricing_chart!O36 -> 267 | X29: =pricing_chart!K36/(1-analysis!$X$26) -> 266.66667 | Y29: =IF(X29<W29,0,X29-W29) -> 0 | AB29: =AB6 -> School Uniform(girls) | AC29: =pricing_chart!T36/pricing_chart!U36 -> 0.6039604 | AD29: =pricing_chart!U36 -> 303 | AE29: =pricing_chart!S36/(1-analysis!$AE$26) -> 300 | AF29: =IF(AE29<AD29,0,AE29-AD29) -> 0 | AH29: =AH6 -> School Uniform(girls) | AI29: =pricing_chart!V36/pricing_chart!W36 -> 0.73856209 | AJ29: =pricing_chart!W36 -> 459 | AK29: =(pricing_chart!S36/(1-analysis!$AK$26)) -> 266.66667 | AL29: =IF(AK29<AJ29,0,AK29-AJ29) -> 0
C30: =C7 -> Kurti | D30: =pricing_chart!D37/pricing_chart!E37 -> 0.55223881 | E30: =pricing_chart!E37 -> 201 | F30: =pricing_chart!C37/(1-analysis!$F$26) -> 180 | G30: =IF(F30<E30,0,F30-E30) -> 0 | I30: =I7 -> Kurti | J30: =pricing_chart!F37/pricing_chart!G37 -> 0.71142747 | K30: =pricing_chart!G37 -> 311.88 | L30: =pricing_chart!C37/(1-analysis!$L$26) -> 180 | M30: =IF(L30<K30,0,L30-K30) -> 0 | O30: =O7 -> T-Shirt | P30: =pricing_chart!L37/pricing_chart!M37 -> 0.57831325 | Q30: =pricing_chart!M37 -> 166 | R30: =pricing_chart!K37/(1-analysis!$R$26) -> 140 | S30: =IF(R30<Q30,0,R30-Q30) -> 0 | U30: =U7 -> T-Shirt | V30: =pricing_chart!N37/pricing_chart!O37 -> 0.55128205 | W30: =pricing_chart!O37 -> 156 | X30: =pricing_chart!K37/(1-analysis!$X$26) -> 155.55556 | Y30: =IF(X30<W30,0,X30-W30) -> 0 | AB30: =AB7 -> School Uniform(Boys) | AC30: =pricing_chart!T37/pricing_chart!U37 -> 0.6 | AD30: =pricing_chart!U37 -> 275 | AE30: =pricing_chart!S37/(1-analysis!$AE$26) -> 275 | AF30: =IF(AE30<AD30,0,AE30-AD30) -> 0 | AH30: =AH7 -> School Uniform(Boys) | AI30: =pricing_chart!V37/pricing_chart!W37 -> 0.73365617 | AJ30: =pricing_chart!W37 -> 413 | AK30: =(pricing_chart!S37/(1-analysis!$AK$26)) -> 244.44444 | AL30: =IF(AK30<AJ30,0,AK30-AJ30) -> 0
C31: =C8 -> Kurti sets | D31: =pricing_chart!D38/pricing_chart!E38 -> 0.62318841 | E31: =pricing_chart!E38 -> 345 | F31: =pricing_chart!C38/(1-analysis!$F$26) -> 260 | G31: =IF(F31<E31,0,F31-E31) -> 0 | I31: =I8 -> Kurti sets | J31: =pricing_chart!F38/pricing_chart!G38 -> 0.70561594 | K31: =pricing_chart!G38 -> 441.6 | L31: =pricing_chart!C38/(1-analysis!$L$26) -> 260 | M31: =IF(L31<K31,0,L31-K31) -> 0 | O31: =O8 -> Vest | P31: =pricing_chart!L38/pricing_chart!M38 -> 0.45652174 | Q31: =pricing_chart!M38 -> 92 | R31: =pricing_chart!K38/(1-analysis!$R$26) -> 100 | S31: =IF(R31<Q31,0,R31-Q31) -> 8 | U31: =U8 -> Vest | V31: =pricing_chart!N38/pricing_chart!O38 -> 0.54954955 | W31: =pricing_chart!O38 -> 111 | X31: =pricing_chart!K38/(1-analysis!$X$26) -> 111.11111 | Y31: =IF(X31<W31,0,X31-W31) -> 0.11111111 | AB31: =AB8 -> Uniform - Men | AC31: =pricing_chart!T38/pricing_chart!U38 -> 0.5157385 | AD31: =pricing_chart!U38 -> 413 | AE31: =pricing_chart!S38/(1-analysis!$AE$26) -> 500 | AF31: =IF(AE31<AD31,0,AE31-AD31) -> 87 | AH31: =AH8 -> Uniform - Men | AI31: =pricing_chart!V38/pricing_chart!W38 -> 0.68 | AJ31: =pricing_chart!W38 -> 625 | AK31: =(pricing_chart!S38/(1-analysis!$AK$26)) -> 444.44444 | AL31: =IF(AK31<AJ31,0,AK31-AJ31) -> 0
C32: =C9 -> Salwar / Anarkali suits | D32: =pricing_chart!D39/pricing_chart!E39 -> 0.65583174 | E32: =pricing_chart!E39 -> 523 | F32: =pricing_chart!C39/(1-analysis!$F$26) -> 360 | G32: =IF(F32<E32,0,F32-E32) -> 0 | I32: =I9 -> Salwar / Anarkali suits | J32: =pricing_chart!F39/pricing_chart!G39 -> 0.68443198 | K32: =pricing_chart!G39 -> 570.4 | L32: =pricing_chart!C39/(1-analysis!$L$26) -> 360 | M32: =IF(L32<K32,0,L32-K32) -> 0 | O32: =O9 -> Dhoti | P32: =pricing_chart!L39/pricing_chart!M39 -> 0.45652174 | Q32: =pricing_chart!M39 -> 92 | R32: =pricing_chart!K39/(1-analysis!$R$26) -> 100 | S32: =IF(R32<Q32,0,R32-Q32) -> 8 | U32: =U9 -> Dhoti | V32: =pricing_chart!N39/pricing_chart!O39 -> 0.54954955 | W32: =pricing_chart!O39 -> 111 | X32: =pricing_chart!K39/(1-analysis!$X$26) -> 111.11111 | Y32: =IF(X32<W32,0,X32-W32) -> 0.11111111 | AB32: =AB9 -> Uniform - Women | AC32: =pricing_chart!T39/pricing_chart!U39 -> 0.50953678 | AD32: =pricing_chart!U39 -> 367 | AE32: =pricing_chart!S39/(1-analysis!$AE$26) -> 450 | AF32: =IF(AE32<AD32,0,AE32-AD32) -> 83 | AH32: =AH9 -> Uniform - Women | AI32: =pricing_chart!V39/pricing_chart!W39 -> 0.67332123 | AJ32: =pricing_chart!W39 -> 551 | AK32: =(pricing_chart!S39/(1-analysis!$AK$26)) -> 400 | AL32: =IF(AK32<AJ32,0,AK32-AJ32) -> 0
C33: =C10 -> Co-Ords / Fusions | D33: =pricing_chart!D40/pricing_chart!E40 -> 0.55307263 | E33: =pricing_chart!E40 -> 358 | F33: =pricing_chart!C40/(1-analysis!$F$26) -> 320 | G33: =IF(F33<E33,0,F33-E33) -> 0 | I33: =I10 -> Co-Ords / Fusions | J33: =pricing_chart!F40/pricing_chart!G40 -> 0.63993159 | K33: =pricing_chart!G40 -> 444.36 | L33: =pricing_chart!C40/(1-analysis!$L$26) -> 320 | M33: =IF(L33<K33,0,L33-K33) -> 0 | O33: =O10 -> Kurta (Basic) | P33: =pricing_chart!L40/pricing_chart!M40 -> 0.53307393 | Q33: =pricing_chart!M40 -> 257 | R33: =pricing_chart!K40/(1-analysis!$R$26) -> 240 | S33: =IF(R33<Q33,0,R33-Q33) -> 0 | U33: =U10 -> Kurta (Basic) | V33: =pricing_chart!N40/pricing_chart!O40 -> 0.5505618 | W33: =pricing_chart!O40 -> 267 | X33: =pricing_chart!K40/(1-analysis!$X$26) -> 266.66667 | Y33: =IF(X33<W33,0,X33-W33) -> 0
C34: =C11 -> Leggings / Inskirts | D34: =pricing_chart!D41/pricing_chart!E41 -> 0.62184874 | E34: =pricing_chart!E41 -> 119 | F34: =pricing_chart!C41/(1-analysis!$F$26) -> 90 | G34: =IF(F34<E34,0,F34-E34) -> 0 | I34: =I11 -> Leggings / Inskirts | J34: =pricing_chart!F41/pricing_chart!G41 -> 0.75171044 | K34: =pricing_chart!G41 -> 181.24 | L34: =pricing_chart!C41/(1-analysis!$L$26) -> 90 | M34: =IF(L34<K34,0,L34-K34) -> 0 | O34: =O11 -> Kurta (Premium) | P34: =pricing_chart!L41/pricing_chart!M41 -> 0.66824645 | Q34: =pricing_chart!M41 -> 422 | R34: =pricing_chart!K41/(1-analysis!$R$26) -> 280 | S34: =IF(R34<Q34,0,R34-Q34) -> 0 | U34: =U11 -> Kurta (Premium) | V34: =pricing_chart!N41/pricing_chart!O41 -> 0.54983923 | W34: =pricing_chart!O41 -> 311 | X34: =pricing_chart!K41/(1-analysis!$X$26) -> 311.11111 | Y34: =IF(X34<W34,0,X34-W34) -> 0.11111111
C35: =C12 -> Skirt | D35: =pricing_chart!D42/pricing_chart!E42 -> 0.59770115 | E35: =pricing_chart!E42 -> 174 | F35: =pricing_chart!C42/(1-analysis!$F$26) -> 140 | G35: =IF(F35<E35,0,F35-E35) -> 0 | I35: =I12 -> Skirt | J35: =pricing_chart!F42/pricing_chart!G42 -> 0.74552857 | K35: =pricing_chart!G42 -> 275.08 | L35: =pricing_chart!C42/(1-analysis!$L$26) -> 140 | M35: =IF(L35<K35,0,L35-K35) -> 0 | O35: =O12 -> Sherwani (Basic) | P35: =pricing_chart!L42/pricing_chart!M42 -> 0.59211421 | Q35: =pricing_chart!M42 -> 1471 | R35: =pricing_chart!K42/(1-analysis!$R$26) -> 1200 | S35: =IF(R35<Q35,0,R35-Q35) -> 0 | U35: =U12 -> Sherwani (Basic) | V35: =pricing_chart!N42/pricing_chart!O42 -> 0.54988747 | W35: =pricing_chart!O42 -> 1333 | X35: =pricing_chart!K42/(1-analysis!$X$26) -> 1333.3333 | Y35: =IF(X35<W35,0,X35-W35) -> 0.33333333
C36: =C13 -> Blouse | D36: =pricing_chart!D43/pricing_chart!E43 -> 0.56521739 | E36: =pricing_chart!E43 -> 230 | F36: =pricing_chart!C43/(1-analysis!$F$26) -> 200 | G36: =IF(F36<E36,0,F36-E36) -> 0 | I36: =I13 -> Blouse | J36: =pricing_chart!F43/pricing_chart!G43 -> 0.64936886 | K36: =pricing_chart!G43 -> 285.2 | L36: =pricing_chart!C43/(1-analysis!$L$26) -> 200 | M36: =IF(L36<K36,0,L36-K36) -> 0 | O36: =O13 -> Sherwani (Premium) | P36: =pricing_chart!L43/pricing_chart!M43 -> 0.66356108 | Q36: =pricing_chart!M43 -> 1932 | R36: =pricing_chart!K43/(1-analysis!$R$26) -> 1300 | S36: =IF(R36<Q36,0,R36-Q36) -> 0 | U36: =U13 -> Sherwani (Premium) | V36: =pricing_chart!N43/pricing_chart!O43 -> 0.5498615 | W36: =pricing_chart!O43 -> 1444 | X36: =pricing_chart!K43/(1-analysis!$X$26) -> 1444.4444 | Y36: =IF(X36<W36,0,X36-W36) -> 0.44444444
C37: =C14 -> Designer / Blouse | D37: =pricing_chart!D44/pricing_chart!E44 -> 0.51690821 | E37: =pricing_chart!E44 -> 414 | F37: =pricing_chart!C44/(1-analysis!$F$26) -> 400 | G37: =IF(F37<E37,0,F37-E37) -> 0 | I37: =I14 -> Designer / Blouse | J37: =pricing_chart!F44/pricing_chart!G44 -> 0.61794147 | K37: =pricing_chart!G44 -> 523.48 | L37: =pricing_chart!C44/(1-analysis!$L$26) -> 400 | M37: =IF(L37<K37,0,L37-K37) -> 0 | O37: =O14 -> Pant (Basic) | P37: =pricing_chart!L44/pricing_chart!M44 -> 0.62857143 | Q37: =pricing_chart!M44 -> 350 | R37: =pricing_chart!K44/(1-analysis!$R$26) -> 260 | S37: =IF(R37<Q37,0,R37-Q37) -> 0 | U37: =U14 -> Pant (Basic) | V37: =pricing_chart!N44/pricing_chart!O44 -> 0.55017301 | W37: =pricing_chart!O44 -> 289 | X37: =pricing_chart!K44/(1-analysis!$X$26) -> 288.88889 | Y37: =IF(X37<W37,0,X37-W37) -> 0
C38: =C15 -> Innerwears | D38: =pricing_chart!D45/pricing_chart!E45 -> 0.58549223 | E38: =pricing_chart!E45 -> 193 | F38: =pricing_chart!C45/(1-analysis!$F$26) -> 160 | G38: =IF(F38<E38,0,F38-E38) -> 0 | I38: =I15 -> Innerwears | J38: =pricing_chart!F45/pricing_chart!G45 -> 0.68030691 | K38: =pricing_chart!G45 -> 250.24 | L38: =pricing_chart!C45/(1-analysis!$L$26) -> 160 | M38: =IF(L38<K38,0,L38-K38) -> 0 | O38: =O15 -> Pant (Premium) | P38: =pricing_chart!L45/pricing_chart!M45 -> 0.68599034 | Q38: =pricing_chart!M45 -> 414 | R38: =pricing_chart!K45/(1-analysis!$R$26) -> 260 | S38: =IF(R38<Q38,0,R38-Q38) -> 0 | U38: =U15 -> Pant (Premium) | V38: =pricing_chart!N45/pricing_chart!O45 -> 0.55017301 | W38: =pricing_chart!O45 -> 289 | X38: =pricing_chart!K45/(1-analysis!$X$26) -> 288.88889 | Y38: =IF(X38<W38,0,X38-W38) -> 0
C39: =C16 -> T-shirts | D39: =pricing_chart!D46/pricing_chart!E46 -> 0.5483871 | E39: =pricing_chart!E46 -> 155 | F39: =pricing_chart!C46/(1-analysis!$F$26) -> 140 | G39: =IF(F39<E39,0,F39-E39) -> 0 | I39: =I16 -> T-shirts | J39: =pricing_chart!F46/pricing_chart!G46 -> 0.65257097 | K39: =pricing_chart!G46 -> 201.48 | L39: =pricing_chart!C46/(1-analysis!$L$26) -> 140 | M39: =IF(L39<K39,0,L39-K39) -> 0 | O39: =O16 -> Shot / Trousers (Basic) | P39: =pricing_chart!L46/pricing_chart!M46 -> 0.50819672 | Q39: =pricing_chart!M46 -> 183 | R39: =pricing_chart!K46/(1-analysis!$R$26) -> 180 | S39: =IF(R39<Q39,0,R39-Q39) -> 0 | U39: =U16 -> Shot / Trousers (Basic) | V39: =pricing_chart!N46/pricing_chart!O46 -> 0.55 | W39: =pricing_chart!O46 -> 200 | X39: =pricing_chart!K46/(1-analysis!$X$26) -> 200 | Y39: =IF(X39<W39,0,X39-W39) -> 2.8421709e-14
C40: =C17 -> Shots | D40: =pricing_chart!D47/pricing_chart!E47 -> 0.47368421 | E40: =pricing_chart!E47 -> 152 | F40: =pricing_chart!C47/(1-analysis!$F$26) -> 160 | G40: =IF(F40<E40,0,F40-E40) -> 8 | I40: =I17 -> Shots | J40: =pricing_chart!F47/pricing_chart!G47 -> 0.65077702 | K40: =pricing_chart!G47 -> 229.08 | L40: =pricing_chart!C47/(1-analysis!$L$26) -> 160 | M40: =IF(L40<K40,0,L40-K40) -> 0 | O40: =O17 -> Shot / Trousers (Premium) | P40: =pricing_chart!L47/pricing_chart!M47 -> 0.53703704 | Q40: =pricing_chart!M47 -> 216 | R40: =pricing_chart!K47/(1-analysis!$R$26) -> 200 | S40: =IF(R40<Q40,0,R40-Q40) -> 0 | U40: =U17 -> Shot / Trousers (Premium) | V40: =pricing_chart!N47/pricing_chart!O47 -> 0.54954955 | W40: =pricing_chart!O47 -> 222 | X40: =pricing_chart!K47/(1-analysis!$X$26) -> 222.22222 | Y40: =IF(X40<W40,0,X40-W40) -> 0.22222222
C41: =C18 -> Trousers / Track pants | D41: =pricing_chart!D48/pricing_chart!E48 -> 0.52830189 | E41: =pricing_chart!E48 -> 212 | F41: =pricing_chart!C48/(1-analysis!$F$26) -> 200 | G41: =IF(F41<E41,0,F41-E41) -> 0 | I41: =I18 -> Trousers / Track pants | J41: =pricing_chart!F48/pricing_chart!G48 -> 0.64244851 | K41: =pricing_chart!G48 -> 279.68 | L41: =pricing_chart!C48/(1-analysis!$L$26) -> 200 | M41: =IF(L41<K41,0,L41-K41) -> 0
C42: =C19 -> Formal Shirts & Pants set | D42: =pricing_chart!D49/pricing_chart!E49 -> 0.46308725 | E42: =pricing_chart!E49 -> 745 | F42: =pricing_chart!C49/(1-analysis!$F$26) -> 800 | G42: =IF(F42<E42,0,F42-E42) -> 55 | I42: =I19 -> Formal Shirts & Pants set | J42: =pricing_chart!F49/pricing_chart!G49 -> 0.56521739 | K42: =pricing_chart!G49 -> 920 | L42: =pricing_chart!C49/(1-analysis!$L$26) -> 800 | M42: =IF(L42<K42,0,L42-K42) -> 0
C43: =C20 -> Nightwear / Loungewear | D43: =pricing_chart!D50/pricing_chart!E50 -> 0.5951417 | E43: =pricing_chart!E50 -> 247 | F43: =pricing_chart!C50/(1-analysis!$F$26) -> 200 | G43: =IF(F43<E43,0,F43-E43) -> 0 | I43: =I20 -> Nightwear / Loungewear | J43: =pricing_chart!F50/pricing_chart!G50 -> 0.72757982 | K43: =pricing_chart!G50 -> 367.08 | L43: =pricing_chart!C50/(1-analysis!$L$26) -> 200 | M43: =IF(L43<K43,0,L43-K43) -> 0
C44: =C21 -> Lehanga Set | D44: =pricing_chart!D51/pricing_chart!E51 -> 0.45652174 | E44: =pricing_chart!E51 -> 920 | F44: =pricing_chart!C51/(1-analysis!$F$26) -> 1000 | G44: =IF(F44<E44,0,F44-E44) -> 80 | I44: =I21 -> Lehanga Set | J44: =pricing_chart!F51/pricing_chart!G51 -> 0.58161797 | K44: =pricing_chart!G51 -> 1195.08 | L44: =pricing_chart!C51/(1-analysis!$L$26) -> 1000 | M44: =IF(L44<K44,0,L44-K44) -> 0
C45: =C22 -> Half Saree | D45: =pricing_chart!D52/pricing_chart!E52 -> 0.57678356 | E45: =pricing_chart!E52 -> 827 | F45: =pricing_chart!C52/(1-analysis!$F$26) -> 700 | G45: =IF(F45<E45,0,F45-E45) -> 0 | I45: =I22 -> Half Saree | J45: =pricing_chart!F52/pricing_chart!G52 -> 0.6191844 | K45: =pricing_chart!G52 -> 919.08 | L45: =pricing_chart!C52/(1-analysis!$L$26) -> 700 | M45: =IF(L45<K45,0,L45-K45) -> 0
F48: Min Margin % | L48: Min Margin % | R48: Min Margin % | X48: Min Margin % | AE48: Min Margin % | AK48: Min Margin %
F49: 0.5 | L49: 0.6 | R49: 0.4 | X49: 0.5 | AE49: 0.4 | AK49: 0.5
C51: Category | D51: Profit Margin B2B | E51: Actual sale Price | G51: Price Change Required | I51: Category | J51: Profit Margin B2C | K51: Actual sale Price | M51: Price Change Required | O51: Category | P51: Profit Margin B2B | Q51: Actual sale Price | S51: Price Change Required | U51: Category | V51: Profit Margin B2C | W51: Actual sale Price | Y51: Price Change Required | AB51: Category | AC51: Profit Margin B2B | AD51: Actual sale Price | AF51: Price Change Required | AH51: Category | AI51: Profit Margin B2C | AJ51: Actual sale Price | AL51: Price Change Required
C52: =C29 -> Short Kurti | D52: =pricing_chart!D59/pricing_chart!E59 -> 0.47552448 | E52: =pricing_chart!E59 -> 143 | F52: =pricing_chart!C59/(1-analysis!$F$49) -> 150 | G52: =G55 -> 0 | I52: =I29 -> Short Kurti | J52: =pricing_chart!F59/pricing_chart!G59 -> 0.64454976 | K52: =pricing_chart!G59 -> 211 | L52: =pricing_chart!C59/(1-analysis!$L$49) -> 187.5 | M52: =IF(L52<K52,0,L52-K52) -> 0 | O52: =O29 -> Shirt | P52: =pricing_chart!L59/pricing_chart!M59 -> 0.43396226 | Q52: =pricing_chart!M59 -> 212 | R52: =pricing_chart!K59/(1-analysis!$R$49) -> 200 | S52: =IF(R52<Q52,0,R52-Q52) -> 0 | U52: =U29 -> Shirt | V52: =pricing_chart!N59/pricing_chart!O59 -> 0.51219512 | W52: =pricing_chart!O59 -> 246 | X52: =pricing_chart!K59/(1-analysis!$X$49) -> 240 | Y52: =IF(X52<W52,0,X52-W52) -> 0 | AB52: =AB29 -> School Uniform(girls) | AC52: =pricing_chart!T59/pricing_chart!U59 -> 0.56989247 | AD52: =pricing_chart!U59 -> 279 | AE52: =pricing_chart!S59/(1-analysis!$AE$49) -> 200 | AF52: =IF(AE52<AD52,0,AE52-AD52) -> 0 | AH52: =AH29 -> School Uniform(girls) | AI52: =pricing_chart!V59/pricing_chart!W59 -> 0.71563981 | AJ52: =pricing_chart!W59 -> 422 | AK52: =(pricing_chart!S59/(1-analysis!$AK$49)) -> 240 | AL52: =IF(AK52<AJ52,0,AK52-AJ52) -> 0
C53: =C30 -> Kurti | D53: =pricing_chart!D60/pricing_chart!E60 -> 0.51351351 | E53: =pricing_chart!E60 -> 185 | F53: =pricing_chart!C60/(1-analysis!$F$49) -> 180 | G53: =IF(F53<E53,0,F53-E53) -> 0 | I53: =I30 -> Kurti | J53: =pricing_chart!F60/pricing_chart!G60 -> 0.68641115 | K53: =pricing_chart!G60 -> 287 | L53: =pricing_chart!C60/(1-analysis!$L$49) -> 225 | M53: =IF(L53<K53,0,L53-K53) -> 0 | O53: =O30 -> T-Shirt | P53: =pricing_chart!L60/pricing_chart!M60 -> 0.54248366 | Q53: =pricing_chart!M60 -> 153 | R53: =pricing_chart!K60/(1-analysis!$R$49) -> 116.66667 | S53: =IF(R53<Q53,0,R53-Q53) -> 0 | U53: =U30 -> T-Shirt | V53: =pricing_chart!N60/pricing_chart!O60 -> 0.51388889 | W53: =pricing_chart!O60 -> 144 | X53: =pricing_chart!K60/(1-analysis!$X$49) -> 140 | Y53: =IF(X53<W53,0,X53-W53) -> 0 | AB53: =AB30 -> School Uniform(Boys) | AC53: =pricing_chart!T60/pricing_chart!U60 -> 0.56521739 | AD53: =pricing_chart!U60 -> 253 | AE53: =pricing_chart!S60/(1-analysis!$AE$49) -> 183.33333 | AF53: =IF(AE53<AD53,0,AE53-AD53) -> 0 | AH53: =AH30 -> School Uniform(Boys) | AI53: =pricing_chart!V55/pricing_chart!W55 -> #DIV/0! | AJ53: =pricing_chart!W60 -> 380 | AK53: =(pricing_chart!S60/(1-analysis!$AK$49)) -> 220 | AL53: =IF(AK53<AJ53,0,AK53-AJ53) -> 0
C54: =C31 -> Kurti sets | D54: =pricing_chart!D61/pricing_chart!E61 -> 0.58990536 | E54: =pricing_chart!E61 -> 317 | F54: =pricing_chart!C61/(1-analysis!$F$49) -> 260 | G54: =IF(F54<E54,0,F54-E54) -> 0 | I54: =I31 -> Kurti sets | J54: =pricing_chart!F61/pricing_chart!G61 -> 0.67980296 | K54: =pricing_chart!G61 -> 406 | L54: =pricing_chart!C61/(1-analysis!$L$49) -> 325 | M54: =IF(L54<K54,0,L54-K54) -> 0 | O54: =O31 -> Vest | P54: =pricing_chart!L61/pricing_chart!M61 -> 0.41176471 | Q54: =pricing_chart!M61 -> 85 | R54: =pricing_chart!K61/(1-analysis!$R$49) -> 83.333333 | S54: =IF(R54<Q54,0,R54-Q54) -> 0 | U54: =U31 -> Vest | V54: =pricing_chart!N61/pricing_chart!O61 -> 0.50980392 | W54: =pricing_chart!O61 -> 102 | X54: =pricing_chart!K61/(1-analysis!$X$49) -> 100 | Y54: =IF(X54<W54,0,X54-W54) -> 0 | AB54: =AB31 -> Uniform - Men | AC54: =pricing_chart!T61/pricing_chart!U61 -> 0.47368421 | AD54: =pricing_chart!U61 -> 380 | AE54: =pricing_chart!S61/(1-analysis!$AE$49) -> 333.33333 | AF54: =IF(AE54<AD54,0,AE54-AD54) -> 0 | AH54: =AH31 -> Uniform - Men | AI54: =pricing_chart!V56/pricing_chart!W56 -> #DIV/0! | AJ54: =pricing_chart!W61 -> 575 | AK54: =(pricing_chart!S61/(1-analysis!$AK$49)) -> 400 | AL54: =IF(AK54<AJ54,0,AK54-AJ54) -> 0
C55: =C32 -> Salwar / Anarkali suits | D55: =pricing_chart!D62/pricing_chart!E62 -> 0.62577963 | E55: =pricing_chart!E62 -> 481 | F55: =pricing_chart!C62/(1-analysis!$F$49) -> 360 | G55: =IF(F55<E55,0,F55-E55) -> 0 | I55: =I32 -> Salwar / Anarkali suits | J55: =pricing_chart!F62/pricing_chart!G62 -> 0.65714286 | K55: =pricing_chart!G62 -> 525 | L55: =pricing_chart!C62/(1-analysis!$L$49) -> 450 | M55: =IF(L55<K55,0,L55-K55) -> 0 | O55: =O32 -> Dhoti | P55: =pricing_chart!L62/pricing_chart!M62 -> 0.41176471 | Q55: =pricing_chart!M62 -> 85 | R55: =pricing_chart!K62/(1-analysis!$R$49) -> 83.333333 | S55: =IF(R55<Q55,0,R55-Q55) -> 0 | U55: =U32 -> Dhoti | V55: =pricing_chart!N62/pricing_chart!O62 -> 0.50980392 | W55: =pricing_chart!O62 -> 102 | X55: =pricing_chart!K62/(1-analysis!$X$49) -> 100 | Y55: =IF(X55<W55,0,X55-W55) -> 0 | AB55: =AB32 -> Uniform - Women | AC55: =pricing_chart!T62/pricing_chart!U62 -> 0.46745562 | AD55: =pricing_chart!U62 -> 338 | AE55: =pricing_chart!S62/(1-analysis!$AE$49) -> 300 | AF55: =IF(AE55<AD55,0,AE55-AD55) -> 0 | AH55: =AH32 -> Uniform - Women | AI55: =pricing_chart!V57/pricing_chart!W57 -> #DIV/0! | AJ55: =pricing_chart!W62 -> 507 | AK55: =(pricing_chart!S62/(1-analysis!$AK$49)) -> 360 | AL55: =IF(AK55<AJ55,0,AK55-AJ55) -> 0
C56: =C33 -> Co-Ords / Fusions | D56: =pricing_chart!D63/pricing_chart!E63 -> 0.51367781 | E56: =pricing_chart!E63 -> 329 | F56: =pricing_chart!C63/(1-analysis!$F$49) -> 320 | G56: =IF(F56<E56,0,F56-E56) -> 0 | I56: =I33 -> Co-Ords / Fusions | J56: =pricing_chart!F63/pricing_chart!G63 -> 0.60880196 | K56: =pricing_chart!G63 -> 409 | L56: =pricing_chart!C63/(1-analysis!$L$49) -> 400 | M56: =IF(L56<K56,0,L56-K56) -> 0 | O56: =O33 -> Kurta (Basic) | P56: =pricing_chart!L63/pricing_chart!M63 -> 0.49152542 | Q56: =pricing_chart!M63 -> 236 | R56: =pricing_chart!K63/(1-analysis!$R$49) -> 200 | S56: =IF(R56<Q56,0,R56-Q56) -> 0 | U56: =U33 -> Kurta (Basic) | V56: =pricing_chart!N63/pricing_chart!O63 -> 0.51219512 | W56: =pricing_chart!O63 -> 246 | X56: =pricing_chart!K63/(1-analysis!$X$49) -> 240 | Y56: =IF(X56<W56,0,X56-W56) -> 0
C57: =C34 -> Leggings / Inskirts | D57: =pricing_chart!D64/pricing_chart!E64 -> 0.58715596 | E57: =pricing_chart!E64 -> 109 | F57: =pricing_chart!C64/(1-analysis!$F$49) -> 90 | G57: =IF(F57<E57,0,F57-E57) -> 0 | I57: =I34 -> Leggings / Inskirts | J57: =pricing_chart!F64/pricing_chart!G64 -> 0.73053892 | K57: =pricing_chart!G64 -> 167 | L57: =pricing_chart!C64/(1-analysis!$L$49) -> 112.5 | M57: =IF(L57<K57,0,L57-K57) -> 0 | O57: =O34 -> Kurta (Premium) | P57: =pricing_chart!L64/pricing_chart!M64 -> 0.63917526 | Q57: =pricing_chart!M64 -> 388 | R57: =pricing_chart!K64/(1-analysis!$R$49) -> 233.33333 | S57: =IF(R57<Q57,0,R57-Q57) -> 0 | U57: =U34 -> Kurta (Premium) | V57: =pricing_chart!N64/pricing_chart!O64 -> 0.51048951 | W57: =pricing_chart!O64 -> 286 | X57: =pricing_chart!K64/(1-analysis!$X$49) -> 280 | Y57: =IF(X57<W57,0,X57-W57) -> 0
C58: =C35 -> Skirt | D58: =pricing_chart!D65/pricing_chart!E65 -> 0.5625 | E58: =pricing_chart!E65 -> 160 | F58: =pricing_chart!C65/(1-analysis!$F$49) -> 140 | G58: =IF(F58<E58,0,F58-E58) -> 0 | I58: =I35 -> Skirt | J58: =pricing_chart!F65/pricing_chart!G65 -> 0.72332016 | K58: =pricing_chart!G65 -> 253 | L58: =pricing_chart!C65/(1-analysis!$L$49) -> 175 | M58: =IF(L58<K58,0,L58-K58) -> 0 | O58: =O35 -> Sherwani (Basic) | P58: =pricing_chart!L65/pricing_chart!M65 -> 0.55654102 | Q58: =pricing_chart!M65 -> 1353 | R58: =pricing_chart!K65/(1-analysis!$R$49) -> 1000 | S58: =IF(R58<Q58,0,R58-Q58) -> 0 | U58: =U35 -> Sherwani (Basic) | V58: =pricing_chart!N65/pricing_chart!O65 -> 0.51060359 | W58: =pricing_chart!O65 -> 1226 | X58: =pricing_chart!K65/(1-analysis!$X$49) -> 1200 | Y58: =IF(X58<W58,0,X58-W58) -> 0
C59: =C36 -> Blouse | D59: =pricing_chart!D66/pricing_chart!E66 -> 0.52830189 | E59: =pricing_chart!E66 -> 212 | F59: =pricing_chart!C66/(1-analysis!$F$49) -> 200 | G59: =IF(F59<E59,0,F59-E59) -> 0 | I59: =I36 -> Blouse | J59: =pricing_chart!F66/pricing_chart!G66 -> 0.61832061 | K59: =pricing_chart!G66 -> 262 | L59: =pricing_chart!C66/(1-analysis!$L$49) -> 250 | M59: =IF(L59<K59,0,L59-K59) -> 0 | O59: =O36 -> Sherwani (Premium) | P59: =pricing_chart!L66/pricing_chart!M66 -> 0.63421497 | Q59: =pricing_chart!M66 -> 1777 | R59: =pricing_chart!K66/(1-analysis!$R$49) -> 1083.3333 | S59: =IF(R59<Q59,0,R59-Q59) -> 0 | U59: =U36 -> Sherwani (Premium) | V59: =pricing_chart!N66/pricing_chart!O66 -> 0.51054217 | W59: =pricing_chart!O66 -> 1328 | X59: =pricing_chart!K66/(1-analysis!$X$49) -> 1300 | Y59: =IF(X59<W59,0,X59-W59) -> 0
C60: =C37 -> Designer / Blouse | D60: =pricing_chart!D67/pricing_chart!E67 -> 0.47506562 | E60: =pricing_chart!E67 -> 381 | F60: =pricing_chart!C67/(1-analysis!$F$49) -> 400 | G60: =IF(F60<E60,0,F60-E60) -> 19 | I60: =I37 -> Designer / Blouse | J60: =pricing_chart!F67/pricing_chart!G67 -> 0.58506224 | K60: =pricing_chart!G67 -> 482 | L60: =pricing_chart!C67/(1-analysis!$L$49) -> 500 | M60: =IF(L60<K60,0,L60-K60) -> 18 | O60: =O37 -> Pant (Basic) | P60: =pricing_chart!L67/pricing_chart!M67 -> 0.59627329 | Q60: =pricing_chart!M67 -> 322 | R60: =pricing_chart!K67/(1-analysis!$R$49) -> 216.66667 | S60: =IF(R60<Q60,0,R60-Q60) -> 0 | U60: =U37 -> Pant (Basic) | V60: =pricing_chart!N67/pricing_chart!O67 -> 0.5112782 | W60: =pricing_chart!O67 -> 266 | X60: =pricing_chart!K67/(1-analysis!$X$49) -> 260 | Y60: =IF(X60<W60,0,X60-W60) -> 0
C61: =C38 -> Innerwears | D61: =pricing_chart!D68/pricing_chart!E68 -> 0.5505618 | E61: =pricing_chart!E68 -> 178 | F61: =pricing_chart!C68/(1-analysis!$F$49) -> 160 | G61: =IF(F61<E61,0,F61-E61) -> 0 | I61: =I38 -> Innerwears | J61: =pricing_chart!F68/pricing_chart!G68 -> 0.65217391 | K61: =pricing_chart!G68 -> 230 | L61: =pricing_chart!C68/(1-analysis!$L$49) -> 200 | M61: =IF(L61<K61,0,L61-K61) -> 0 | O61: =O38 -> Pant (Premium) | P61: =pricing_chart!L68/pricing_chart!M68 -> 0.65879265 | Q61: =pricing_chart!M68 -> 381 | R61: =pricing_chart!K68/(1-analysis!$R$49) -> 216.66667 | S61: =IF(R61<Q61,0,R61-Q61) -> 0 | U61: =U38 -> Pant (Premium) | V61: =pricing_chart!N68/pricing_chart!O68 -> 0.5112782 | W61: =pricing_chart!O68 -> 266 | X61: =pricing_chart!K68/(1-analysis!$X$49) -> 260 | Y61: =IF(X61<W61,0,X61-W61) -> 0
C62: =C39 -> T-shirts | D62: =pricing_chart!D69/pricing_chart!E69 -> 0.51048951 | E62: =pricing_chart!E69 -> 143 | F62: =pricing_chart!C69/(1-analysis!$F$49) -> 140 | G62: =IF(F62<E62,0,F62-E62) -> 0 | I62: =I39 -> T-shirts | J62: =pricing_chart!F69/pricing_chart!G69 -> 0.62162162 | K62: =pricing_chart!G69 -> 185 | L62: =pricing_chart!C69/(1-analysis!$L$49) -> 175 | M62: =IF(L62<K62,0,L62-K62) -> 0 | O62: =O39 -> Shot / Trousers (Basic) | P62: =pricing_chart!L69/pricing_chart!M69 -> 0.46428571 | Q62: =pricing_chart!M69 -> 168 | R62: =pricing_chart!K69/(1-analysis!$R$49) -> 150 | S62: =IF(R62<Q62,0,R62-Q62) -> 0 | U62: =U39 -> Shot / Trousers (Basic) | V62: =pricing_chart!N69/pricing_chart!O69 -> 0.51086957 | W62: =pricing_chart!O69 -> 184 | X62: =pricing_chart!K69/(1-analysis!$X$49) -> 180 | Y62: =IF(X62<W62,0,X62-W62) -> 0
C63: =C40 -> Shots | D63: =pricing_chart!D70/pricing_chart!E70 -> 0.42857143 | E63: =pricing_chart!E70 -> 140 | F63: =pricing_chart!C70/(1-analysis!$F$49) -> 160 | G63: =IF(F63<E63,0,F63-E63) -> 20 | I63: =I40 -> Shots | J63: =pricing_chart!F70/pricing_chart!G70 -> 0.62085308 | K63: =pricing_chart!G70 -> 211 | L63: =pricing_chart!C70/(1-analysis!$L$49) -> 200 | M63: =IF(L63<K63,0,L63-K63) -> 0 | O63: =O40 -> Shot / Trousers (Premium) | P63: =pricing_chart!L70/pricing_chart!M70 -> 0.49748744 | Q63: =pricing_chart!M70 -> 199 | R63: =pricing_chart!K70/(1-analysis!$R$49) -> 166.66667 | S63: =IF(R63<Q63,0,R63-Q63) -> 0 | U63: =U40 -> Shot / Trousers (Premium) | V63: =pricing_chart!N70/pricing_chart!O70 -> 0.50980392 | W63: =pricing_chart!O70 -> 204 | X63: =pricing_chart!K70/(1-analysis!$X$49) -> 200 | Y63: =IF(X63<W63,0,X63-W63) -> 0
C64: =C41 -> Trousers / Track pants | D64: =pricing_chart!D71/pricing_chart!E71 -> 0.48717949 | E64: =pricing_chart!E71 -> 195 | F64: =pricing_chart!C71/(1-analysis!$F$49) -> 200 | G64: =IF(F64<E64,0,F64-E64) -> 5 | I64: =I41 -> Trousers / Track pants | J64: =pricing_chart!F71/pricing_chart!G71 -> 0.61089494 | K64: =pricing_chart!G71 -> 257 | L64: =pricing_chart!C71/(1-analysis!$L$49) -> 250 | M64: =IF(L64<K64,0,L64-K64) -> 0
C65: =C42 -> Formal Shirts & Pants set | D65: =pricing_chart!D72/pricing_chart!E72 -> 0.7080292 | E65: =pricing_chart!E72 -> 685 | F65: =pricing_chart!C72/(1-analysis!$F$49) -> 400 | G65: =IF(F65<E65,0,F65-E65) -> 0 | I65: =I42 -> Formal Shirts & Pants set | J65: =pricing_chart!F72/pricing_chart!G72 -> 0.76359338 | K65: =pricing_chart!G72 -> 846 | L65: =pricing_chart!C72/(1-analysis!$L$49) -> 500 | M65: =IF(L65<K65,0,L65-K65) -> 0
C66: =C43 -> Nightwear / Loungewear | D66: =pricing_chart!D73/pricing_chart!E73 -> 0.55947137 | E66: =pricing_chart!E73 -> 227 | F66: =pricing_chart!C73/(1-analysis!$F$49) -> 200 | G66: =IF(F66<E66,0,F66-E66) -> 0 | I66: =I43 -> Nightwear / Loungewear | J66: =pricing_chart!F73/pricing_chart!G73 -> 0.70414201 | K66: =pricing_chart!G73 -> 338 | L66: =pricing_chart!C73/(1-analysis!$L$49) -> 250 | M66: =IF(L66<K66,0,L66-K66) -> 0
C67: =C44 -> Lehanga Set | D67: =pricing_chart!D74/pricing_chart!E74 -> 0.40898345 | E67: =pricing_chart!E74 -> 846 | F67: =pricing_chart!C74/(1-analysis!$F$49) -> 1000 | G67: =IF(F67<E67,0,F67-E67) -> 154 | I67: =I44 -> Lehanga Set | J67: =pricing_chart!F74/pricing_chart!G74 -> 0.54504095 | K67: =pricing_chart!G74 -> 1099 | L67: =pricing_chart!C74/(1-analysis!$L$49) -> 1250 | M67: =IF(L67<K67,0,L67-K67) -> 151
C68: =C45 -> Half Saree | D68: =pricing_chart!D75/pricing_chart!E75 -> 0.54007884 | E68: =pricing_chart!E75 -> 761 | F68: =pricing_chart!C75/(1-analysis!$F$49) -> 700 | G68: =IF(F68<E68,0,F68-E68) -> 0 | I68: =I45 -> Half Saree | J68: =pricing_chart!F75/pricing_chart!G75 -> 0.58628842 | K68: =pricing_chart!G75 -> 846 | L68: =pricing_chart!C75/(1-analysis!$L$49) -> 875 | M68: =IF(L68<K68,0,L68-K68) -> 29

Sheet Sheet1
